henrys_model_utils/__init__.py
henrys_model_utils/mselossflat.py
henrys_model_utils/reshape.py
henrys_model_utils-0.1.dist-info/LICENSE.txt
henrys_model_utils-0.1.dist-info/METADATA
henrys_model_utils-0.1.dist-info/WHEEL
henrys_model_utils-0.1.dist-info/top_level.txt
henrys_model_utils-0.1.dist-info/RECORD
